tometrics/__init__.py
tometrics/tometrics.py
tometrics/lib/__init__.py
tometrics/lib/generic_interface.py
tometrics/lib/influxdb.py
tometrics/lib/metric.py
tometrics-0.0.6.dist-info/LICENSE
tometrics-0.0.6.dist-info/METADATA
tometrics-0.0.6.dist-info/WHEEL
tometrics-0.0.6.dist-info/top_level.txt
tometrics-0.0.6.dist-info/RECORD
