Metadata-Version: 2.1
Name: tometrics
Version: 0.0.6
Summary: Simple metrics abstraction
Requires-Python: >=3.6
License-File: LICENSE
Requires-Dist: requests
Requires-Dist: requests-toolbelt
